MANIFEST.in
README.rst
setup.py
CGEA/CGEA.py
CGEA/__init__.py
CGEA/test.py
CGEA.egg-info/PKG-INFO
CGEA.egg-info/Pubmed_NLP_queries
CGEA.egg-info/SOURCES.txt
CGEA.egg-info/dependency_links.txt
CGEA.egg-info/not-zip-safe
CGEA.egg-info/requires.txt
CGEA.egg-info/top_level.txt
CGEA/lib/CGEAdata.py
CGEA/lib/CGEAdata.pyc
CGEA/lib/SimpleMapReduce.pyc
CGEA/lib/__init__.py
CGEA/lib/__init__.pyc
CGEA/lib/drugListProcessing.py
CGEA/lib/drugListProcessing.pyc
CGEA/lib/errorHandling.pyc
CGEA/lib/featureBasedCGEA.py
CGEA/lib/featureBasedCGEA.pyc
CGEA/lib/featureListProcessing.py
CGEA/lib/featureListProcessing.pyc
CGEA/lib/file.py
CGEA/lib/file.pyc
CGEA/lib/fishersBasedCGEA.py
CGEA/lib/fishersBasedCGEA.pyc
CGEA/lib/log.py
CGEA/lib/log.pyc
CGEA/lib/remakeMixmdl_1309.py
CGEA/lib/statistics.py
CGEA/lib/statistics.pyc