Metadata-Version: 1.0
Name: CGEA
Version: 0.917
Summary: Chemo Genomic Enrichment Analysis
Home-page: https://bitbucket.org/MaxTomlinson/cgea
Author: Max Tomlinson / Ben Readhead
Author-email: max.tomlinson@mssm.edu
License: MIT
Platform: UNKNOWN
